Metadata-Version: 2.1
Name: weatherlab
Version: 0.1.0
Summary: Simple poker game in pure python
Home-page: https://gitlab.com/zodiacfireworks/weatherlab-extension
Author: Martin Vuelta
Author-email: Martin Vuelta <zodiacfireworks@softbutterfly.io>
License: UNKNOWN
Download-URL: https://gitlab.com/zodiacfireworks/weatherlab-extension/archive/0.1.0.tar.gz
Keywords: Poker
Platform: UNKNOWN
Classifier: Development Status :: 3 - Alpha
Classifier: Intended Audience :: Developers
Classifier: License :: OSI Approved :: BSD License
Classifier: Natural Language :: English
Classifier: Programming Language :: Python :: 3.7
Classifier: Programming Language :: Python :: 3.8
Classifier: Topic :: Software Development :: Libraries :: Python Modules
Requires: ipython
